[
  {
    "id": "7cb6fd24-0378-4a1c-b46f-a44196b5f6b3",
    "name": "Miss Annie Haley",
    "phone": "(360) 230-4372",
    "email": "Roselyn42@yahoo.com",
    "job": "Regional Interactions Agent"
  },
  {
    "id": "12ddfe0f-2285-4f47-8c40-c9e871f42412",
    "name": "Hazel Ruecker IV",
    "phone": "(868) 917-8576 x0251",
    "email": "Theron9@hotmail.com",
    "job": "Forward Marketing Supervisor"
  },
  {
    "id": "aa13d57c-cdb5-45e1-b829-c7573a6d3f73",
    "name": "Ms. Claudia Beier",
    "phone": "1-349-668-3354",
    "email": "Icie_Hauck@hotmail.com",
    "job": "Corporate Accounts Consultant"
  },
  {
    "id": "c8798515-42bf-4c39-acba-78543c69e3c2",
    "name": "Eduardo Smitham",
    "phone": "296-305-9655 x6877",
    "email": "Earl.Heathcote65@hotmail.com",
    "job": "Dynamic Quality Architect"
  },
  {
    "id": "8c2da7e1-1988-43d9-988f-3ffd9817bfeb",
    "name": "Monica Gottlieb",
    "phone": "1-200-423-4130 x549",
    "email": "Arlie.Jacobs@hotmail.com",
    "job": "Lead Response Orchestrator"
  },
  {
    "id": "e5826644-a219-4fb6-9c17-b96f6fad9782",
    "name": "Tasha Hickle",
    "phone": "789-600-4925 x2754",
    "email": "Savannah_Stanton16@gmail.com",
    "job": "Investor Interactions Orchestrator"
  },
  {
    "id": "fae44786-eca0-4afd-a139-e7a9bc4aaf98",
    "name": "Leo Ankunding",
    "phone": "(508) 387-2407 x11541",
    "email": "Marvin97@yahoo.com",
    "job": "Internal Implementation Consultant"
  },
  {
    "id": "0557dc9c-6e59-40ce-8d6e-0d36b013147f",
    "name": "Willard Lesch PhD",
    "phone": "1-676-546-2245 x234",
    "email": "Elliot80@gmail.com",
    "job": "District Program Developer"
  },
  {
    "id": "41da89c8-4d01-4bf2-9b93-636216b54995",
    "name": "Kay Rau PhD",
    "phone": "795.650.0651 x3985",
    "email": "Margot66@hotmail.com",
    "job": "Internal Security Engineer"
  },
  {
    "id": "e96b3dd5-53a1-4569-851c-fda42af22852",
    "name": "Minnie Ankunding",
    "phone": "1-942-288-6740 x05880",
    "email": "Ryann_Rau96@gmail.com",
    "job": "District Integration Agent"
  },
  {
    "id": "9fa28a23-b2b6-451b-8143-7ee705e6ad74",
    "name": "Becky Cummerata-Leannon",
    "phone": "665.561.6079",
    "email": "Kraig.Kshlerin35@gmail.com",
    "job": "International Accountability Producer"
  },
  {
    "id": "ab41becf-7d4c-4d0b-9cc2-e4f97b90d984",
    "name": "Elvira Kemmer-Veum",
    "phone": "875.805.2752 x660",
    "email": "Geraldine.Keeling28@yahoo.com",
    "job": "International Accountability Designer"
  }
]